codeeval_adjudication_engine/__init__.py
codeeval_adjudication_engine/auditing.py
codeeval_adjudication_engine/consensus.py
codeeval_adjudication_engine/interfaces.py
codeeval_adjudication_engine/models.py
codeeval_adjudication_engine/notifiers.py
codeeval_adjudication_engine/overrides.py
codeeval_adjudication_engine/presenter.py
codeeval_adjudication_engine/recorder.py
codeeval_adjudication_engine/tgs_factory.py
codeeval_adjudication_engine/tracker.py
codeeval_adjudication_engine/workflow_manager.py
codeeval_adjudication_engine-0.0.1.dist-info/METADATA
codeeval_adjudication_engine-0.0.1.dist-info/WHEEL
codeeval_adjudication_engine-0.0.1.dist-info/licenses/LICENSE
codeeval_adjudication_engine-0.0.1.dist-info/licenses/NOTICE
codeeval_adjudication_engine-0.0.1.dist-info/RECORD
