Metadata-Version: 2.4
Name: codeeval_adjudication_engine
Version: 0.0.1
Summary: Manages the business logic for the review workflow, ensures randomized and blinded presentation of the Delta, records votes with robust concurrency control (Pessimistic Locking), calculates consensus based on defined rules, handles operational overrides, and constructs the True Gold Standard (TGS).
Project-URL: Homepage, https://github.com/gowthamrao/codeeval_adjudication_engine
Project-URL: Repository, https://github.com/gowthamrao/codeeval_adjudication_engine
License: Prosperity Public License
License-File: LICENSE
License-File: NOTICE
Classifier: Development Status :: 3 - Alpha
Classifier: Intended Audience :: Developers
Classifier: License :: OSI Approved :: MIT License
Classifier: Operating System :: OS Independent
Classifier: Programming Language :: Python :: 3
Classifier: Programming Language :: Python :: 3.8
Classifier: Programming Language :: Python :: 3.9
Classifier: Programming Language :: Python :: 3.10
Classifier: Programming Language :: Python :: 3.11
Classifier: Topic :: Software Development :: Build Tools
Requires-Python: >=3.8
Provides-Extra: dev
Requires-Dist: black; extra == 'dev'
Requires-Dist: flake8; extra == 'dev'
Requires-Dist: isort; extra == 'dev'
Requires-Dist: pytest; extra == 'dev'
Requires-Dist: pytest-cov; extra == 'dev'
